{
  "app": "vitrine",
  "version": 1,
  "generatedAt": "2026-07-13T19:22:56.181Z",
  "cards": [
    {
      "id": "card-2027-s3-gold-glove-cf",
      "cardName": "Julio Rodriguez - Gold Glove",
      "year": "2027",
      "cardNumber": "#791",
      "series": "3",
      "cardSet": "",
      "brand": "Topps",
      "type": "Base",
      "team": "Seattle Mariners",
      "category": "Hitter",
      "position": "CF",
      "rookie": false,
      "additional": "",
      "batterStats": "",
      "pitcherStats": "",
      "showBatter": false,
      "showPitcher": false,
      "coating": "matte",
      "pattern": "crackle",
      "foilOpacity": 0.85,
      "bezel": 18,
      "aspect": 0.6708033964728936,
      "front": "2027 S3 Gold Glove CF.png",
      "back": null,
      "mask": null
    },
    {
      "id": "card-2027-s3-gold-glove-pitcher",
      "cardName": "Logan Gilbert - Gold Glove",
      "year": "2027",
      "cardNumber": "#720",
      "series": "3",
      "cardSet": "",
      "brand": "Topps",
      "type": "Base",
      "team": "Seattle Mariners",
      "category": "Pitcher",
      "position": "P",
      "rookie": false,
      "additional": "",
      "batterStats": "",
      "pitcherStats": "",
      "showBatter": false,
      "showPitcher": false,
      "coating": "matte",
      "pattern": "crackle",
      "foilOpacity": 0.85,
      "bezel": 18,
      "aspect": 0.6681877444589309,
      "front": "2027 S3 Gold Glove Pitcher.png",
      "back": null,
      "mask": null
    },
    {
      "id": "card-2027-s3-gold-glove-catcher",
      "cardName": "Cal Raleigh - Gold Glove",
      "year": "2027",
      "cardNumber": "#708",
      "series": "3",
      "cardSet": "",
      "brand": "Topps",
      "type": "Base",
      "team": "Seattle Mariners",
      "category": "Hitter",
      "position": "C",
      "rookie": false,
      "additional": "",
      "batterStats": "",
      "pitcherStats": "",
      "showBatter": false,
      "showPitcher": false,
      "coating": "matte",
      "pattern": "crackle",
      "foilOpacity": 0.85,
      "bezel": 18,
      "aspect": 0.6697127937336814,
      "front": "2027 S3 Gold Glove Catcher.png",
      "back": null,
      "mask": null
    },
    {
      "id": "card-2027-s3-pennant",
      "cardName": "AMerican League Pennant Winners",
      "year": "2027",
      "cardNumber": "#850",
      "series": "3",
      "cardSet": "",
      "brand": "Topps",
      "type": "Base",
      "team": "Seattle Mariners",
      "category": "Team",
      "position": "",
      "rookie": false,
      "additional": "",
      "batterStats": "",
      "pitcherStats": "",
      "showBatter": false,
      "showPitcher": false,
      "coating": "matte",
      "pattern": "crackle",
      "foilOpacity": 0.85,
      "bezel": 18,
      "aspect": 1.4266666666666667,
      "front": "2027 S3 Pennant.jpg",
      "back": null,
      "mask": null
    },
    {
      "id": "card-2027-s3-lazmon",
      "cardName": "Lazaro Montes",
      "year": "2027",
      "cardNumber": "#601",
      "series": "3",
      "cardSet": "",
      "brand": "Topps",
      "type": "Base",
      "team": "Seatle Mariners",
      "category": "Prospect",
      "position": "OF",
      "rookie": false,
      "additional": "",
      "batterStats": "",
      "pitcherStats": "",
      "showBatter": false,
      "showPitcher": false,
      "coating": "matte",
      "pattern": "crackle",
      "foilOpacity": 0.85,
      "bezel": 16,
      "aspect": 0.6932270916334662,
      "front": "2027 S3 LazMon.jpg",
      "back": null,
      "mask": null
    },
    {
      "id": "card-2027-s3-coleme",
      "cardName": "Colt Emerson",
      "year": "2027",
      "cardNumber": "#811",
      "series": "3",
      "cardSet": "",
      "brand": "Topps",
      "type": "Base",
      "team": "Seattle Mariners",
      "category": "Rookie",
      "position": "SS",
      "rookie": false,
      "additional": "",
      "batterStats": "",
      "pitcherStats": "",
      "showBatter": false,
      "showPitcher": false,
      "coating": "matte",
      "pattern": "crackle",
      "foilOpacity": 0.85,
      "bezel": 18,
      "aspect": 0.6932270916334662,
      "front": "2027 S3 ColEme.jpg",
      "back": null,
      "mask": null
    },
    {
      "id": "card-2027-s1-gabspe",
      "cardName": "Gabe Speier",
      "year": "2027",
      "cardNumber": "#233",
      "series": "1",
      "cardSet": "",
      "brand": "Topps",
      "type": "Base",
      "team": "Seattle Mariners",
      "category": "Pitcher",
      "position": "RP",
      "rookie": false,
      "additional": "",
      "batterStats": "",
      "pitcherStats": "",
      "showBatter": false,
      "showPitcher": false,
      "coating": "matte",
      "pattern": "crackle",
      "foilOpacity": 0.85,
      "bezel": 18,
      "aspect": 0.6932270916334662,
      "front": "2027 S1 GabSpe.jpg",
      "back": null,
      "mask": null
    },
    {
      "id": "card-2027-s1-calral",
      "cardName": "Cal Raleigh",
      "year": "2027",
      "cardNumber": "#104",
      "series": "1",
      "cardSet": "",
      "brand": "Topps",
      "type": "Base",
      "team": "Seattle Mariners",
      "category": "Hitter",
      "position": "C",
      "rookie": false,
      "additional": "",
      "batterStats": "",
      "pitcherStats": "",
      "showBatter": false,
      "showPitcher": false,
      "coating": "matte",
      "pattern": "crackle",
      "foilOpacity": 0.85,
      "bezel": 18,
      "aspect": 0.6932270916334662,
      "front": "2027 S1 CalRal.jpg",
      "back": null,
      "mask": null
    },
    {
      "id": "card-2027-s1-fregon",
      "cardName": "Freddy Gonzalez",
      "year": "2027",
      "cardNumber": "#163",
      "series": "1",
      "cardSet": "",
      "brand": "Topps",
      "type": "Base",
      "team": "Seattle Mariners",
      "category": "Hitter",
      "position": "3B",
      "rookie": false,
      "additional": "",
      "batterStats": "",
      "pitcherStats": "",
      "showBatter": false,
      "showPitcher": false,
      "coating": "matte",
      "pattern": "crackle",
      "foilOpacity": 0.85,
      "bezel": 18,
      "aspect": 0.6932270916334662,
      "front": "2027 S1 FreGon.jpg",
      "back": null,
      "mask": null
    },
    {
      "id": "card-2027-s1-josnay",
      "cardName": "Josh Naylor",
      "year": "2027",
      "cardNumber": "#160",
      "series": "1",
      "cardSet": "",
      "brand": "Topps",
      "type": "Base",
      "team": "Seattle Mariners",
      "category": "Hitter",
      "position": "1B",
      "rookie": false,
      "additional": "",
      "batterStats": "",
      "pitcherStats": "",
      "showBatter": false,
      "showPitcher": false,
      "coating": "matte",
      "pattern": "crackle",
      "foilOpacity": 0.85,
      "bezel": 18,
      "aspect": 0.6932270916334662,
      "front": "2027 S1 JosNay.jpg",
      "back": null,
      "mask": null
    },
    {
      "id": "card-2027-s1-geokir",
      "cardName": "George Kirby",
      "year": "2027",
      "cardNumber": "#183",
      "series": "1",
      "cardSet": "",
      "brand": "Topps",
      "type": "Base",
      "team": "Seattle Mariners",
      "category": "Pitcher",
      "position": "SP",
      "rookie": false,
      "additional": "",
      "batterStats": "",
      "pitcherStats": "",
      "showBatter": false,
      "showPitcher": false,
      "coating": "matte",
      "pattern": "crackle",
      "foilOpacity": 0.85,
      "bezel": 18,
      "aspect": 0.6932270916334662,
      "front": "2027 S1 GeoKir.jpg",
      "back": null,
      "mask": null
    },
    {
      "id": "card-2027-s2-luicas",
      "cardName": "Luis Castillo",
      "year": "2027",
      "cardNumber": "#470",
      "series": "2",
      "cardSet": "",
      "brand": "Topps",
      "type": "Base",
      "team": "Seattle Mariners",
      "category": "Pitcher",
      "position": "SP",
      "rookie": false,
      "additional": "",
      "batterStats": "",
      "pitcherStats": "",
      "showBatter": false,
      "showPitcher": false,
      "coating": "matte",
      "pattern": "crackle",
      "foilOpacity": 0.85,
      "bezel": 16,
      "aspect": 0.6932270916334662,
      "front": "2027 S2 LuiCas.jpg",
      "back": null,
      "mask": null
    },
    {
      "id": "card-2027-s2-loggil",
      "cardName": "Logan Gilbert",
      "year": "2027",
      "cardNumber": "#402",
      "series": "2",
      "cardSet": "",
      "brand": "Topps",
      "type": "Base",
      "team": "Seattle Mariners",
      "category": "Pitcher",
      "position": "SP",
      "rookie": false,
      "additional": "",
      "batterStats": "",
      "pitcherStats": "",
      "showBatter": false,
      "showPitcher": false,
      "coating": "matte",
      "pattern": "crackle",
      "foilOpacity": 0.85,
      "bezel": 18,
      "aspect": 0.6932270916334662,
      "front": "2027 S2 LogGil.jpg",
      "back": null,
      "mask": null
    },
    {
      "id": "card-2027-s1-brywoo",
      "cardName": "Bryan Woo",
      "year": "2027",
      "cardNumber": "#085",
      "series": "1",
      "cardSet": "",
      "brand": "Topps",
      "type": "Base",
      "team": "Seattle Mariners",
      "category": "Pitcher",
      "position": "SP",
      "rookie": false,
      "additional": "",
      "batterStats": "",
      "pitcherStats": "",
      "showBatter": false,
      "showPitcher": false,
      "coating": "matte",
      "pattern": "starburst",
      "foilOpacity": 0.22,
      "bezel": 18,
      "aspect": 0.6932270916334662,
      "front": "2027 S1 BryWoo.jpg",
      "back": null,
      "mask": null
    },
    {
      "id": "card-2027-s1-antvol",
      "cardName": "Anthony Volpe",
      "year": "2027",
      "cardNumber": "#101",
      "series": "1",
      "cardSet": "",
      "brand": "Topps",
      "type": "Base",
      "team": "Seattle Mariners",
      "category": "Hitter",
      "position": "SS",
      "rookie": false,
      "additional": "",
      "batterStats": "",
      "pitcherStats": "",
      "showBatter": false,
      "showPitcher": false,
      "coating": "matte",
      "pattern": "pulsar",
      "foilOpacity": 0.35,
      "bezel": 18,
      "aspect": 0.6932270916334662,
      "front": "2027 S1 AntVol.jpg",
      "back": null,
      "mask": null
    },
    {
      "id": "card-2027-s1-jrod",
      "cardName": "Julio Rodriguez",
      "year": "2027",
      "cardNumber": "#020",
      "series": "1",
      "cardSet": "",
      "brand": "Topps",
      "type": "Base",
      "team": "Seattle Mariners",
      "category": "Hitter",
      "position": "OF",
      "rookie": false,
      "additional": "",
      "batterStats": "",
      "pitcherStats": "",
      "showBatter": false,
      "showPitcher": false,
      "coating": "matte",
      "pattern": "crackle",
      "foilOpacity": 0.85,
      "bezel": 18,
      "aspect": 0.6932270916334662,
      "front": "2027 S1 JRod.jpg",
      "back": null,
      "mask": null
    },
    {
      "id": "card-2027-s1-nicpiv",
      "cardName": "Nick Pivetta",
      "year": "2027",
      "cardNumber": "#150",
      "series": "1",
      "cardSet": "",
      "brand": "Topps",
      "type": "Base",
      "team": "Seattle Mariners",
      "category": "Pitcher",
      "position": "SP",
      "rookie": false,
      "additional": "",
      "batterStats": "",
      "pitcherStats": "",
      "showBatter": false,
      "showPitcher": false,
      "coating": "matte",
      "pattern": "crackle",
      "foilOpacity": 0.85,
      "bezel": 18,
      "aspect": 0.6932270916334662,
      "front": "2027 S1 NicPiv.jpg",
      "back": null,
      "mask": null
    },
    {
      "id": "card-2027-s2-andmun",
      "cardName": "Andres Munoz",
      "year": "2027",
      "cardNumber": "#079",
      "series": "1",
      "cardSet": "",
      "brand": "Topps",
      "type": "Base",
      "team": "Seattle Mariners",
      "category": "Pitcher",
      "position": "RP",
      "rookie": false,
      "additional": "",
      "batterStats": "",
      "pitcherStats": "",
      "showBatter": false,
      "showPitcher": false,
      "coating": "matte",
      "pattern": "crackle",
      "foilOpacity": 0.85,
      "bezel": 18,
      "aspect": 0.6932270916334662,
      "front": "2027 S2 AndMun.jpg",
      "back": null,
      "mask": null
    },
    {
      "id": "card-2027-s2-jacsuw",
      "cardName": "Jack Suwinski",
      "year": "2027",
      "cardNumber": "#341",
      "series": "2",
      "cardSet": "",
      "brand": "",
      "type": "",
      "team": "Seattle Mariners",
      "category": "Hitter",
      "position": "OF",
      "rookie": false,
      "additional": "",
      "batterStats": "",
      "pitcherStats": "",
      "showBatter": false,
      "showPitcher": false,
      "coating": "matte",
      "pattern": "crackle",
      "foilOpacity": 0.85,
      "bezel": 18,
      "aspect": 0.6932270916334662,
      "front": "2027 S2 JacSuw.jpg",
      "back": null,
      "mask": null
    },
    {
      "id": "card-original-card",
      "cardName": "Original Card",
      "year": "",
      "cardNumber": "",
      "series": "",
      "cardSet": "",
      "brand": "",
      "type": "",
      "team": "",
      "category": "",
      "position": "",
      "rookie": false,
      "additional": "",
      "batterStats": "",
      "pitcherStats": "",
      "showBatter": false,
      "showPitcher": false,
      "coating": "matte",
      "pattern": "crackle",
      "foilOpacity": 0.85,
      "bezel": 16,
      "front": "original-card.png",
      "back": null,
      "mask": null
    }
  ]
}